{"stats":{"minecraft:used":{"jeg:service_rifle":243,"minecraft:chest":7,"minecraft:shield":99,"minecraft:iron_sword":158,"minecraft:mutton":1,"minecraft:tuff":15,"jeg:grenade":1,"minecraft:obsidian":26,"minecraft:iron_helmet":4,"jeg:healing_talisman":1,"minecraft:bow":4,"minecraft:jungle_button":1,"minecraft:furnace":16,"minecraft:egg":1,"minecraft:diorite":1,"minecraft:damaged_anvil":2,"minecraft:blackstone":108,"minecraft:golden_apple":8,"jeg:gunmetal_workbench":1,"minecraft:sand":1,"minecraft:blast_furnace":1,"minecraft:shears":7,"jeg:recycler":6,"minecraft:lever":3,"minecraft:string":23,"minecraft:bread":124,"minecraft:andesite":11,"minecraft:smithing_table":2,"minecraft:birch_log":1,"minecraft:coarse_dirt":2,"minecraft:bone_meal":145,"minecraft:experience_bottle":7,"minecraft:enchanting_table":1,"minecraft:flint_and_steel":2,"ageofweapons:warhammer_iron":38,"jeg:schematic_station":1,"minecraft:netherrack":28,"minecraft:orange_bed":2,"minecraft:torch":43,"scalinghealth:heart_crystal":2,"minecraft:dirt":11,"jeg:gunnite_workbench":1,"jeg:blueprint_workbench":1,"minecraft:jungle_trapdoor":12,"minecraft:wooden_axe":21,"minecraft:iron_axe":87,"scalinghealth:power_crystal":1,"minecraft:barrel":9,"ageofweapons:multi_tool_iron":170,"minecraft:bamboo":36,"minecraft:tripwire_hook":7,"ageofweapons:cleaver_iron":120,"minecraft:cooked_beef":1,"minecraft:cobbled_deepslate":204,"sophisticatedbackpacks:gold_backpack":1,"minecraft:cooked_mutton":4,"minecraft:water_bucket":95,"minecraft:baked_potato":1,"scalinghealth:chance_heart":2,"minecraft:stonecutter":3,"minecraft:cracked_stone_bricks":2,"minecraft:polished_blackstone_bricks":9,"minecraft:music_disc_cat":1,"jeg:ammo_box":5,"minecraft:crafting_table":10,"minecraft:bamboo_block":7,"minecraft:cod":1,"minecraft:smoker":2,"wandering_bags:chalice_of_swine":1,"minecraft:flower_pot":2,"minecraft:diamond_pickaxe":2806,"minecraft:apple":10,"minecraft:cracked_polished_blackstone_bricks":10,"minecraft:iron_pickaxe":95,"jeg:scrap_workbench":1,"minecraft:potion":2,"minecraft:cobblestone":111,"minecraft:turtle_helmet":2,"minecraft:bucket":95,"minecraft:yellow_bed":2,"minecraft:brush":2,"minecraft:jukebox":1},"minecraft:dropped":{"minecraft:porkchop":6,"minecraft:glass_bottle":1,"minecraft:leather":1,"minecraft:jungle_planks":20,"jeg:scrap":7,"minecraft:flint":1,"jeg:scrap_workbench":1,"minecraft:crimson_roots":1,"minecraft:bone_meal":5,"minecraft:sand":5,"minecraft:iron_pickaxe":1,"minecraft:gold_ingot":5,"minecraft:wheat":64,"minecraft:obsidian":1,"minecraft:rotten_flesh":37,"jeg:rifle_ammo":192,"minecraft:gunpowder":36,"jeg:assault_rifle":1,"minecraft:iron_ore":3,"minecraft:arrow":9,"jeg:repeating_shotgun":1,"ageofweapons:multi_tool_iron":2,"minecraft:enchanted_book":1,"minecraft:bread":320,"minecraft:iron_ingot":6,"minecraft:wheat_seeds":4,"ageofweapons:cleaver_iron":1,"minecraft:mossy_cobblestone":1,"minecraft:cobblestone":3,"minecraft:acacia_log":8,"minecraft:torch":1,"minecraft:string":21,"minecraft:redstone":5,"minecraft:iron_boots":1,"minecraft:spruce_fence":2,"minecraft:pumpkin_seeds":2,"jeg:service_rifle":4,"minecraft:diamond_pickaxe":1,"minecraft:oak_sapling":1,"minecraft:stone_pressure_plate":1,"minecraft:bamboo":81,"jeg:pistol_ammo":43,"minecraft:brick":3},"minecraft:crafted":{"minecraft:jungle_button":1,"minecraft:oak_planks":32,"ageofweapons:blank_template":99,"minecraft:stone":103,"minecraft:lever":1,"jeg:gunmetal_ingot":57,"minecraft:cooked_mutton":12,"minecraft:bamboo_block":16,"sophisticatedbackpacks:smelting_upgrade":1,"minecraft:iron_boots":1,"minecraft:raw_copper":9,"minecraft:chest":9,"minecraft:copper_block":31,"scalinghealth:power_crystal":1,"ageofweapons:cleaver_iron_part":1,"sophisticatedbackpacks:backpack":2,"ageofweapons:cleaver_iron":2,"minecraft:crafting_table":5,"ageofweapons:small_iron_blank":17,"minecraft:iron_helmet":3,"sophisticatedbackpacks:advanced_feeding_upgrade":1,"minecraft:smithing_table":1,"minecraft:copper_ingot":372,"minecraft:hay_block":69,"sophisticatedbackpacks:upgrade_base":2,"jeg:gunmetal_block":1,"minecraft:bamboo_planks":32,"jeg:brimstone_crystal":116,"minecraft:iron_chestplate":3,"minecraft:charcoal":8,"sophisticatedbackpacks:diamond_backpack":1,"minecraft:stick":24,"minecraft:iron_ingot":145,"sophisticatedbackpacks:auto_smelting_upgrade":1,"minecraft:iron_pickaxe":2,"ageofweapons:multi_tool_iron":3,"minecraft:gold_ingot":33,"minecraft:shears":1,"ageofweapons:multi_tool_template":3,"minecraft:coal":54,"minecraft:tripwire_hook":2,"ageofweapons:tiny_iron_blank":17,"jeg:gunmetal_grit":802,"minecraft:furnace":5,"sophisticatedbackpacks:stack_upgrade_starter_tier":1,"ageofweapons:huge_iron_blank":6,"minecraft:jungle_trapdoor":8,"minecraft:bone_meal":285,"minecraft:raw_copper_block":38,"minecraft:flint_and_steel":1,"ageofweapons:cleaver_template":2,"ageofweapons:warhammer_template":1,"minecraft:iron_axe":1,"ageofweapons:multi_tool_iron_part":3,"sophisticatedbackpacks:iron_backpack":2,"minecraft:wheat":2238,"minecraft:cooked_beef":1,"minecraft:bone_block":15,"jeg:repair_kit":6,"sophisticatedbackpacks:gold_backpack":2,"minecraft:air":0,"minecraft:bread":755,"minecraft:jungle_planks":28,"minecraft:blue_dye":1,"ageofweapons:warhammer_iron":1,"minecraft:raw_gold":9,"ageofweapons:hammer":1,"minecraft:wooden_axe":1,"minecraft:iron_leggings":3,"minecraft:stonecutter":1,"jeg:gunmetal_nugget":549,"minecraft:acacia_planks":4,"minecraft:torch":4,"ageofweapons:medium_iron_blank":17,"minecraft:lapis_block":7},"minecraft:killed":{"minecraft:spider":8,"minecraft:skeleton":15,"minecraft:bee":1,"minecraft:silverfish":5,"minecraft:piglin_brute":4,"jeg:ghoul":6,"minecraft:piglin":1,"minecraft:zombie_villager":2,"minecraft:iron_golem":1,"minecraft:creeper":4,"minecraft:sheep":7,"minecraft:trader_llama":1,"minecraft:zombie":35,"minecraft:ghast":1,"minecraft:cow":3,"minecraft:drowned":1,"minecraft:wandering_trader":1,"minecraft:hoglin":1},"minecraft:killed_by":{"minecraft:zombified_piglin":1,"minecraft:zombie":1},"minecraft:custom":{"lootr:looted_stat":83,"minecraft:interact_with_crafting_table":90,"minecraft:open_barrel":63,"minecraft:bell_ring":1,"minecraft:eat_cake_slice":1,"minecraft:leave_game":99,"minecraft:time_since_death":54759,"minecraft:sprint_one_cm":974209,"minecraft:damage_blocked_by_shield":4216,"minecraft:drop":75,"minecraft:play_noteblock":1,"minecraft:talked_to_villager":4,"minecraft:play_time":426769,"minecraft:deaths":11,"minecraft:jump":4884,"minecraft:walk_on_water_one_cm":59559,"minecraft:interact_with_furnace":245,"minecraft:play_record":1,"minecraft:sleep_in_bed":4,"minecraft:damage_dealt":17298,"minecraft:crouch_one_cm":99540,"minecraft:interact_with_smoker":11,"minecraft:inspect_dispenser":1,"minecraft:interact_with_smithing_table":13,"minecraft:interact_with_anvil":9,"minecraft:mob_kills":105,"minecraft:inspect_hopper":6,"minecraft:interact_with_campfire":4,"minecraft:damage_dealt_resisted":4844,"minecraft:climb_one_cm":10752,"minecraft:walk_one_cm":738366,"minecraft:sneak_time":24873,"minecraft:walk_under_water_one_cm":18483,"minecraft:interact_with_blast_furnace":17,"minecraft:total_world_time":426769,"minecraft:tune_noteblock":1,"minecraft:interact_with_stonecutter":8,"minecraft:time_since_rest":55330,"minecraft:damage_taken":14863,"minecraft:damage_absorbed":235,"minecraft:swim_one_cm":123092,"minecraft:fly_one_cm":956458,"minecraft:open_chest":175,"minecraft:fall_one_cm":145208},"minecraft:picked_up":{"minecraft:wooden_axe":1,"minecraft:wheat":684,"jeg:ammo_box":6,"minecraft:creeper_head":1,"minecraft:flower_pot":5,"minecraft:smithing_table":1,"minecraft:lead":1,"minecraft:gilded_blackstone":2,"minecraft:brewing_stand":1,"minecraft:amethyst_block":23,"minecraft:music_disc_cat":1,"minecraft:string":63,"jeg:blueprint_workbench":1,"minecraft:raw_copper":317,"jeg:recycler":6,"minecraft:gold_nugget":3,"minecraft:cobbled_deepslate":446,"jeg:flare_gun":1,"minecraft:calcite":5,"minecraft:iron_pickaxe":1,"minecraft:coal_block":11,"minecraft:furnace":12,"minecraft:beehive":3,"jeg:service_rifle":3,"minecraft:stick":42,"minecraft:acacia_fence":2,"minecraft:jukebox":2,"jeg:pistol_ammo":65,"minecraft:torch":2,"minecraft:acacia_log":9,"minecraft:spruce_stairs":10,"minecraft:porkchop":6,"minecraft:pointed_dripstone":42,"minecraft:diorite":40,"wandering_bags:piglin_bag":2,"minecraft:yellow_banner":1,"minecraft:orange_bed":2,"jeg:schematic_station":1,"minecraft:rotten_flesh":73,"minecraft:carved_pumpkin":1,"jeg:rifle_ammo":724,"minecraft:obsidian":44,"minecraft:cod":1,"minecraft:iron_bars":6,"minecraft:cobblestone":253,"minecraft:birch_log":3,"minecraft:andesite":37,"minecraft:jungle_log":10,"minecraft:smoker":2,"minecraft:potato":1,"minecraft:flint":2,"minecraft:tuff":60,"jeg:scrap":147,"minecraft:lapis_lazuli":61,"minecraft:dirt":14,"minecraft:lantern":3,"minecraft:stripped_bamboo_block":7,"minecraft:leather_boots":1,"minecraft:bone":37,"minecraft:stonecutter":2,"minecraft:bow":3,"minecraft:wheat_seeds":1673,"minecraft:pink_banner":1,"minecraft:raw_gold":23,"minecraft:grindstone":2,"jeg:gunnite_ingot":8,"minecraft:bamboo":291,"jeg:gunnite_workbench":1,"jeg:flare":1,"jeg:assault_rifle":1,"jeg:blaze_round":16,"minecraft:jungle_planks":20,"minecraft:sand":9,"minecraft:loom":1,"minecraft:red_terracotta":5,"minecraft:barrel":3,"minecraft:mossy_cobblestone":2,"minecraft:dispenser":10,"minecraft:blue_terracotta":7,"minecraft:diamond":5,"minecraft:lever":4,"jeg:skin_crate":1,"minecraft:cracked_polished_blackstone_bricks":10,"minecraft:granite":436,"ageofweapons:medium_iron_blank":17,"minecraft:emerald":2,"minecraft:bread":12,"minecraft:spruce_sign":2,"minecraft:oak_sapling":52,"minecraft:netherrack":602,"minecraft:crimson_roots":2,"minecraft:diamond_pickaxe":1,"sophisticatedbackpacks:gold_backpack":1,"minecraft:coarse_dirt":3,"minecraft:crafting_table":5,"minecraft:azure_bluet":1,"minecraft:turtle_helmet":2,"minecraft:gold_block":2,"jeg:scrap_workbench":2,"minecraft:brick":7,"minecraft:jungle_trapdoor":6,"minecraft:item_frame":2,"minecraft:blackstone":117,"ageofweapons:multi_tool_iron":1,"minecraft:cracked_stone_bricks":4,"minecraft:beef":10,"minecraft:observer":8,"minecraft:iron_nugget":5,"minecraft:spruce_slab":4,"minecraft:sugar_cane":48,"minecraft:chest":3,"minecraft:spruce_trapdoor":5,"minecraft:egg":1,"minecraft:dark_oak_sapling":1,"minecraft:raw_iron":172,"ageofweapons:blank_template":60,"jeg:brimstone_crystal":61,"jeg:scrap_bin":6,"minecraft:spruce_fence":2,"minecraft:polished_blackstone_bricks":25,"minecraft:stone_button":4,"minecraft:redstone":68,"minecraft:stone_pressure_plate":6,"jeg:healing_talisman":2,"minecraft:arrow":30,"minecraft:jungle_stairs":2,"minecraft:nether_bricks":1,"minecraft:hay_block":180,"jeg:gunmetal_workbench":1,"wandering_bags:wandering_bag":1,"minecraft:mutton":13,"jeg:raw_brimstone":192,"minecraft:white_wool":5,"minecraft:air":0,"minecraft:basalt":49,"minecraft:tripwire_hook":5,"minecraft:magenta_banner":1,"minecraft:leather":12,"minecraft:red_mushroom":1,"minecraft:oak_log":96,"minecraft:ancient_debris":1,"minecraft:yellow_bed":3,"minecraft:gunpowder":97,"scalinghealth:heart_crystal":2,"jeg:grenade":1,"minecraft:apple":6,"minecraft:stone_bricks":1,"minecraft:iron_ingot":4,"scalinghealth:power_crystal_shard":14,"minecraft:glass_bottle":1,"minecraft:soul_sand":1,"minecraft:acacia_sapling":1,"jeg:tech_trash":12,"minecraft:book":21,"ageofweapons:multi_tool_template":1,"minecraft:oak_slab":1,"minecraft:smooth_basalt":4,"minecraft:quartz":18,"minecraft:cracked_nether_bricks":1,"minecraft:gravel":3,"minecraft:amethyst_shard":236,"minecraft:white_bed":1,"minecraft:spider_eye":1,"minecraft:cyan_banner":1,"minecraft:lime_banner":1,"minecraft:pumpkin_seeds":2,"jeg:ectoplasm":2,"minecraft:polished_diorite":4,"minecraft:melon_seeds":27,"minecraft:damaged_anvil":2,"minecraft:black_wool":2,"minecraft:coal":188,"minecraft:hopper":4},"minecraft:mined":{"minecraft:large_amethyst_bud":1,"jeg:blueprint_workbench":1,"minecraft:attached_melon_stem":2,"minecraft:stone_pressure_plate":4,"minecraft:white_bed":1,"minecraft:mossy_stone_brick_slab":1,"sophisticatedbackpacks:gold_backpack":1,"minecraft:brewing_stand":1,"minecraft:spruce_trapdoor":5,"minecraft:obsidian":44,"minecraft:granite":439,"minecraft:budding_amethyst":3,"minecraft:acacia_log":9,"minecraft:grass_block":5,"minecraft:jungle_log":6,"minecraft:cracked_polished_blackstone_bricks":11,"minecraft:oak_pressure_plate":1,"minecraft:coal_block":6,"minecraft:polished_diorite":4,"minecraft:hopper":4,"minecraft:oxeye_daisy":1,"minecraft:spawner":2,"minecraft:polished_blackstone_bricks":26,"minecraft:weeping_vines_plant":2,"minecraft:mossy_cobblestone_slab":1,"jeg:ammo_box":5,"minecraft:iron_ore":50,"minecraft:cobbled_deepslate":6,"minecraft:fire":4,"minecraft:cyan_wall_banner":1,"minecraft:potted_red_mushroom":1,"minecraft:iron_bars":6,"scalinghealth:deepslate_power_crystal_ore":10,"minecraft:stripped_bamboo_block":7,"minecraft:spruce_slab":4,"minecraft:tripwire":17,"minecraft:orange_bed":2,"minecraft:jungle_trapdoor":6,"minecraft:deepslate_redstone_ore":11,"lootr:lootr_chest":2,"jeg:scrap_bin":6,"minecraft:blackstone":117,"minecraft:magenta_wall_banner":1,"minecraft:melon_stem":18,"minecraft:smoker":2,"minecraft:crimson_nylium":1,"minecraft:amethyst_cluster":34,"minecraft:blast_furnace":1,"minecraft:calcite":5,"jeg:recycler":6,"minecraft:glass":4,"minecraft:nether_quartz_ore":10,"minecraft:cobblestone":67,"minecraft:damaged_anvil":2,"minecraft:grindstone":2,"minecraft:sugar_cane":17,"minecraft:wall_torch":1,"minecraft:amethyst_block":23,"minecraft:blue_terracotta":7,"minecraft:birch_log":3,"minecraft:wheat":626,"minecraft:jukebox":2,"minecraft:tnt":1,"minecraft:grass":51,"minecraft:oak_log":111,"minecraft:acacia_fence":1,"minecraft:loom":1,"minecraft:sand":2,"minecraft:dispenser":10,"minecraft:smooth_basalt":4,"minecraft:tripwire_hook":2,"minecraft:stonecutter":2,"jeg:gunnite_workbench":1,"minecraft:netherrack":848,"minecraft:ancient_debris":1,"minecraft:oak_leaves":9,"minecraft:deepslate":443,"minecraft:tuff":62,"minecraft:yellow_wall_banner":1,"minecraft:mossy_cobblestone":2,"minecraft:deepslate_diamond_ore":4,"minecraft:lever":1,"minecraft:nether_bricks":1,"jeg:gunmetal_workbench":1,"minecraft:decorated_pot":3,"minecraft:crimson_roots":1,"minecraft:potted_bamboo":2,"minecraft:cracked_nether_bricks":1,"jeg:schematic_station":1,"minecraft:hay_block":140,"minecraft:potted_dark_oak_sapling":1,"minecraft:furnace":11,"minecraft:andesite":38,"minecraft:gold_block":2,"minecraft:bookshelf":7,"minecraft:lime_wall_banner":1,"minecraft:deepslate_iron_ore":12,"minecraft:vine":7,"minecraft:bamboo":408,"minecraft:stone":178,"jeg:blackstone_brimstone_ore":39,"minecraft:smithing_table":1,"minecraft:acacia_leaves":5,"jeg:scrap_ore":33,"lootr:lootr_barrel":3,"minecraft:soul_sand":1,"minecraft:basalt":50,"minecraft:stone_brick_slab":1,"minecraft:observer":8,"jeg:basalt_brimstone_ore":46,"minecraft:crafting_table":5,"minecraft:emerald_ore":1,"minecraft:dropper":1,"minecraft:copper_ore":44,"minecraft:tall_grass":27,"minecraft:lapis_ore":11,"minecraft:deepslate_gold_ore":7,"minecraft:diorite":40,"minecraft:spruce_stairs":10,"jeg:deepslate_scrap_ore":3,"jeg:scrap_workbench":1,"minecraft:red_terracotta":5,"minecraft:coarse_dirt":4,"minecraft:beehive":3,"minecraft:creeper_head":1,"minecraft:pink_wall_banner":1,"minecraft:yellow_bed":3,"minecraft:coal_ore":47,"minecraft:flower_pot":1,"minecraft:gravel":1,"minecraft:gray_carpet":1,"minecraft:cobweb":5,"minecraft:cracked_stone_bricks":5,"minecraft:stone_bricks":1,"minecraft:fern":11},"minecraft:broken":{"minecraft:iron_boots":1,"minecraft:iron_helmet":2}},"DataVersion":3465}